eschercloud/__init__.py
eschercloud/db.py
eschercloud/llms.py
eschercloud-0.1.4.dist-info/METADATA
eschercloud-0.1.4.dist-info/WHEEL
eschercloud-0.1.4.dist-info/top_level.txt
eschercloud-0.1.4.dist-info/RECORD
