Metadata-Version: 2.1
Name: eschercloud
Version: 0.1.4
Summary: Open source llm service
Author: A.S
Author-email: service@eschercloud.ai
Requires-Dist: requests
